vkcoin/__init__.py
vkcoin/vkcoin.py
vkcoin-1.11.1.dist-info/METADATA
vkcoin-1.11.1.dist-info/WHEEL
vkcoin-1.11.1.dist-info/top_level.txt
vkcoin-1.11.1.dist-info/RECORD
