Metadata-Version: 2.1
Name: vkcoin
Version: 1.11.1
Summary: Враппер для платёжного API VK Coin
Home-page: https://github.com/crinny/vkcoin
Author: crinny
Author-email: isfellop@gmail.com
License: UNKNOWN
Platform: UNKNOWN
Classifier: Programming Language :: Python :: 3.6
Requires-Dist: requests
Requires-Dist: websocket-client
Requires-Dist: vk
